generate_sample_csvs.py
aiva_sample_processor-0.1.0.dist-info/licenses/LICENSE
importers/__init__.py
importers/preprocessing_utils.py
aiva_sample_processor-0.1.0.dist-info/METADATA
aiva_sample_processor-0.1.0.dist-info/WHEEL
aiva_sample_processor-0.1.0.dist-info/entry_points.txt
aiva_sample_processor-0.1.0.dist-info/top_level.txt
aiva_sample_processor-0.1.0.dist-info/RECORD
