Metadata-Version: 2.4
Name: aiva-sample-processor
Version: 0.1.0
Summary: OpenCRAVAT CSV processor for generating sample CSVs for aiva-database import
Home-page: https://github.com/MHSPL/aiva-sample-processor
Author: Mamidi Health
Author-email: info@mamidi.co.in
Classifier: Programming Language :: Python :: 3
Classifier: Programming Language :: Python :: 3.8
Classifier: Programming Language :: Python :: 3.9
Classifier: Programming Language :: Python :: 3.10
Classifier: License :: OSI Approved :: MIT License
Classifier: Operating System :: OS Independent
Classifier: Intended Audience :: Science/Research
Classifier: Topic :: Scientific/Engineering :: Bio-Informatics
Requires-Python: >=3.8
License-File: LICENSE
Requires-Dist: requests>=2.25.0
Requires-Dist: pandas>=1.3.0
Requires-Dist: pysam>=0.16.0
Requires-Dist: psycopg2-binary>=2.9.0
Requires-Dist: tqdm>=4.62.0
Requires-Dist: open-cravat>=2.2.0
Requires-Dist: python-dotenv>=0.19.0
Requires-Dist: aiva-vrs>=0.1.0
Dynamic: author
Dynamic: author-email
Dynamic: classifier
Dynamic: description
Dynamic: description-content-type
Dynamic: home-page
Dynamic: license-file
Dynamic: requires-dist
Dynamic: requires-python
Dynamic: summary
